llm_context_providers/__init__.py
llm_context_providers/asana_context_provider.py
llm_context_providers/context_manager.py
llm_context_providers/context_provider.py
tests/__init__.py
tests/test_asana_context_provider.py
tests/test_context_manager.py
llm_context_providers-0.1.1.dist-info/LICENSE
llm_context_providers-0.1.1.dist-info/METADATA
llm_context_providers-0.1.1.dist-info/WHEEL
llm_context_providers-0.1.1.dist-info/top_level.txt
llm_context_providers-0.1.1.dist-info/RECORD
