Metadata-Version: 2.1
Name: llm-context-providers
Version: 0.1.1
Home-page: https://github.com/smankoo/LLMContextProviders
Author: Sumeet Singh Mankoo
Author-email: sumeet@mankoo.ca
License: MIT
Classifier: Programming Language :: Python :: 3
Classifier: License :: OSI Approved :: MIT License
Classifier: Operating System :: OS Independent
License-File: LICENSE
Requires-Dist: asana
Requires-Dist: python-dotenv
Requires-Dist: python-dateutil
Requires-Dist: pytz
Requires-Dist: pyyaml
